config_loader/__init__.py
config_loader/loader.py
tyme_config_loader-0.6.dist-info/METADATA
tyme_config_loader-0.6.dist-info/WHEEL
tyme_config_loader-0.6.dist-info/top_level.txt
tyme_config_loader-0.6.dist-info/RECORD
